cjdk/__init__.py
cjdk/__main__.py
cjdk/_api.py
cjdk/_cache.py
cjdk/_conf.py
cjdk/_download.py
cjdk/_exceptions.py
cjdk/_index.py
cjdk/_install.py
cjdk/_jdk.py
cjdk/_progress.py
cjdk/_utils.py
cjdk/_version.py
cjdk/py.typed
cjdk-0.5.0.dist-info/METADATA
cjdk-0.5.0.dist-info/WHEEL
cjdk-0.5.0.dist-info/entry_points.txt
cjdk-0.5.0.dist-info/licenses/LICENSE.txt
cjdk-0.5.0.dist-info/RECORD
