Metadata-Version: 2.4
Name: cjdk
Version: 0.5.0
Summary: Auto-download JDK or JRE and run Java apps from Python or CLI
Project-URL: Documentation, https://cachedjdk.github.io/cjdk/latest
Project-URL: Repository, https://github.com/cachedjdk/cjdk
Author: Mark A. Tsuchida
License-Expression: MIT
License-File: LICENSE.txt
Keywords: JDK,JRE,JVM,Java
Classifier: Programming Language :: Java
Classifier: Programming Language :: Python :: 3
Classifier: Programming Language :: Python :: 3.10
Classifier: Programming Language :: Python :: 3.11
Classifier: Programming Language :: Python :: 3.12
Classifier: Programming Language :: Python :: 3.13
Classifier: Programming Language :: Python :: 3.14
Classifier: Topic :: Software Development
Requires-Python: >=3.10
Requires-Dist: click>=8.0
Requires-Dist: progressbar2>=4.0
Requires-Dist: requests>=2.24
Requires-Dist: typing-extensions>=4.15.0
